{
  "$schema": "http://json-schema.org/draft-04/schema#",
  "title": "MTDFB - API 56 v1.0 Submit 9-Box Vat Return",
  "description": "Submit 9-Box Vat Return",
  "type": "object",
  "required": [
    "periodKey", "vatDueSales", "vatDueAcquisitions", "vatDueTotal",
    "vatReclaimedCurrPeriod", "vatDueNet", "totalValueSalesExVAT", "totalValuePurchasesExVAT",  "totalValueGoodsSuppliedExVAT", "totalAllAcquisitionsExVAT", "receivedAt"
  ],
  "properties": {
    "periodKey": {
      "title": "The key to identify the return period",
      "description": "A 4 character string identifier, format nnAA or nnAn or #nnn or  nnnn e.g. 17GH, 17B2, #001, 0918 (VMF Period Key, added for VAT Hybrid)",  "type": "string",
      "pattern": "(^[0-9]{2}[A-Z][A-Z0-9]$)|(^#[0-9]{3}$)|(^[0-9]{4}$)"  },
    "vatDueSales": {
      "title": "Vat due on sales",
      "description": "Total VAT due on Total Sales",
      "$ref": "#/definitions/monetaryPosNeg"
    },
    "vatDueAcquisitions": {
      "title": "VAT due on acquisitions",
      "description": "Total VAT due on acquisitions from EC Member States",  "$ref": "#/definitions/monetaryPosNeg"
    },
    "vatDueTotal": {
      "title": "Total VAT due",
      "description": "SUM of (1) and (2) (Calculated by agent software)",  "$ref": "#/definitions/monetaryPosNeg"
    },
    "vatReclaimedCurrPeriod": {
      "title": "Total VAT reclaimed",
      "description": "Total VAT reclaimed on total purchases and other inputs",  "$ref": "#/definitions/monetaryPosNeg"
    },
    "vatDueNet": {
      "title": "Net VAT due",
      "description": "DIFFERENCE between (3) and (4) (Calculated by agent software)",  "$ref": "#/definitions/monetaryPos_13"
    },
    "totalValueSalesExVAT": {
      "title": "Total sales",
      "description": "Total sales excluding VAT (including exempt sales)",  "$ref": "#/definitions/monetaryPosNeg"
    },
    "totalValuePurchasesExVAT": {
      "title": "Total purchases",
      "description": "Total purchases excluding VAT (including exempt purchases)",  "$ref": "#/definitions/monetaryPosNeg"
    },
    "totalValueGoodsSuppliedExVAT": {
      "title": "Total supply",
      "description": "Total supply of goods, excluding VAT, to EC Member States",  "$ref": "#/definitions/monetaryPosNeg"
    },
    "totalAllAcquisitionsExVAT": {
      "title": "Total acquisitions",
      "description": "Total acquisitions of goods, excluding VAT, from EC Member States",  "$ref": "#/definitions/monetaryPosNeg"
    },
    "agentReferenceNumber": {
      "title": "Agent Reference Number",
      "description": "Agent Reference Number. Populated if call is made by Agent and the  Agent has a ARN. The pattern and example are copied from DES API#28 specification",  "type": "string",
      "pattern": "^[A-Z]ARN[0-9]{7}$"
    },
    "receivedAt": {
      "title": "The date & time the return was received by MDTP API",  "description": "The date & time the return was received by MDTP API. UTC timezone",  "type": "string",
      "format": "date-time"
    },
    "uniqueID": {
      "description": "In case of SCAN channel, a unique scan reference ID must be  provided",
      "type": "string",
      "pattern": "^[A-Za-z0-9 \\-,.&'\\/()!]{1,10}$"
    }
  },
  "additionalProperties": false,
  "definitions": {
    "monetaryPos_13": {
      "description": "Defines a monetary value (to 2 decimal places), between 0 and  99,999,999,999.99",
      "type": "number",
      "minimum": 0.00,
      "maximum": 99999999999.99,
      "multipleOf": 0.01
    },
    "monetaryPosNeg": {
      "description": "Defines a monetary value (to 2 decimal places), between  -9,999,999,999,999.99 and 9,999,999,999,999.99",
      "type": "number",
      "minimum": -9999999999999.99,
      "maximum": 9999999999999.99,
      "multipleOf": 0.01
    }
  }
}